tree_sitter_bash/__init__.py
tree_sitter_bash/__init__.pyi
tree_sitter_bash/_binding.abi3.so
tree_sitter_bash/binding.c
tree_sitter_bash/py.typed
tree_sitter_bash/queries/highlights.scm
tree_sitter_bash-0.25.0.dist-info/METADATA
tree_sitter_bash-0.25.0.dist-info/WHEEL
tree_sitter_bash-0.25.0.dist-info/top_level.txt
tree_sitter_bash-0.25.0.dist-info/RECORD
tree_sitter_bash-0.25.0.dist-info/licenses/LICENSE
